{ "DisplayName" : "EARLY AVERAGE STUDENT",
  "EduPersonAffiliations" : [ "member",
      "student",
      "alum",
      "staff",
      "employee"
    ],
  "IsTestEntity" : true,
  "PersonAffiliations" : { "PersonFullURI" : { "DisplayName" : "EARLY AVERAGE STUDENT",
          "Href" : "\/identity\/v1\/person\/AABBCCDDEEFFAABBCCDDEEFFAABBCCDA\/full.json",
          "UWNetID" : "early",
          "UWRegID" : "AABBCCDDEEFFAABBCCDDEEFFAABBCCDA"
        } },
  "PriorUWNetIDs" : [],
  "PriorUWRegIDs" : [],
  "RegisteredFirstMiddleName" : "EARLY AVERAGE",
  "RegisteredName" : "EARLY AVERAGE STUDENT",
  "RegisteredSurname" : "STUDENT",
  "UIDNumber" : "99699",
  "UWNetID" : "early",
  "UWRegID" : "AABBCCDDEEFFAABBCCDDEEFFAABBCCDA",
  "WhitepagesPublish" : true
}
